[{"model": "auth.permission", "pk": 1, "fields": {"name": "Can add log entry", "content_type": 1, "codename": "add_logentry"}}, {"model": "auth.permission", "pk": 2, "fields": {"name": "Can change log entry", "content_type": 1, "codename": "change_logentry"}}, {"model": "auth.permission", "pk": 3, "fields": {"name": "Can delete log entry", "content_type": 1, "codename": "delete_logentry"}}, {"model": "auth.permission", "pk": 4, "fields": {"name": "Can view log entry", "content_type": 1, "codename": "view_logentry"}}, {"model": "auth.permission", "pk": 5, "fields": {"name": "Can add permission", "content_type": 2, "codename": "add_permission"}}, {"model": "auth.permission", "pk": 6, "fields": {"name": "Can change permission", "content_type": 2, "codename": "change_permission"}}, {"model": "auth.permission", "pk": 7, "fields": {"name": "Can delete permission", "content_type": 2, "codename": "delete_permission"}}, {"model": "auth.permission", "pk": 8, "fields": {"name": "Can view permission", "content_type": 2, "codename": "view_permission"}}, {"model": "auth.permission", "pk": 9, "fields": {"name": "Can add group", "content_type": 3, "codename": "add_group"}}, {"model": "auth.permission", "pk": 10, "fields": {"name": "Can change group", "content_type": 3, "codename": "change_group"}}, {"model": "auth.permission", "pk": 11, "fields": {"name": "Can delete group", "content_type": 3, "codename": "delete_group"}}, {"model": "auth.permission", "pk": 12, "fields": {"name": "Can view group", "content_type": 3, "codename": "view_group"}}, {"model": "auth.permission", "pk": 13, "fields": {"name": "Can add content type", "content_type": 4, "codename": "add_contenttype"}}, {"model": "auth.permission", "pk": 14, "fields": {"name": "Can change content type", "content_type": 4, "codename": "change_contenttype"}}, {"model": "auth.permission", "pk": 15, "fields": {"name": "Can delete content type", "content_type": 4, "codename": "delete_contenttype"}}, {"model": "auth.permission", "pk": 16, "fields": {"name": "Can view content type", "content_type": 4, "codename": "view_contenttype"}}, {"model": "auth.permission", "pk": 17, "fields": {"name": "Can add session", "content_type": 5, "codename": "add_session"}}, {"model": "auth.permission", "pk": 18, "fields": {"name": "Can change session", "content_type": 5, "codename": "change_session"}}, {"model": "auth.permission", "pk": 19, "fields": {"name": "Can delete session", "content_type": 5, "codename": "delete_session"}}, {"model": "auth.permission", "pk": 20, "fields": {"name": "Can view session", "content_type": 5, "codename": "view_session"}}, {"model": "auth.permission", "pk": 21, "fields": {"name": "Can add market", "content_type": 6, "codename": "add_market"}}, {"model": "auth.permission", "pk": 22, "fields": {"name": "Can change market", "content_type": 6, "codename": "change_market"}}, {"model": "auth.permission", "pk": 23, "fields": {"name": "Can delete market", "content_type": 6, "codename": "delete_market"}}, {"model": "auth.permission", "pk": 24, "fields": {"name": "Can view market", "content_type": 6, "codename": "view_market"}}, {"model": "auth.permission", "pk": 25, "fields": {"name": "Can add trader", "content_type": 7, "codename": "add_trader"}}, {"model": "auth.permission", "pk": 26, "fields": {"name": "Can change trader", "content_type": 7, "codename": "change_trader"}}, {"model": "auth.permission", "pk": 27, "fields": {"name": "Can delete trader", "content_type": 7, "codename": "delete_trader"}}, {"model": "auth.permission", "pk": 28, "fields": {"name": "Can view trader", "content_type": 7, "codename": "view_trader"}}, {"model": "auth.permission", "pk": 29, "fields": {"name": "Can add trade", "content_type": 8, "codename": "add_trade"}}, {"model": "auth.permission", "pk": 30, "fields": {"name": "Can change trade", "content_type": 8, "codename": "change_trade"}}, {"model": "auth.permission", "pk": 31, "fields": {"name": "Can delete trade", "content_type": 8, "codename": "delete_trade"}}, {"model": "auth.permission", "pk": 32, "fields": {"name": "Can view trade", "content_type": 8, "codename": "view_trade"}}, {"model": "auth.permission", "pk": 33, "fields": {"name": "Can add round stat", "content_type": 9, "codename": "add_roundstat"}}, {"model": "auth.permission", "pk": 34, "fields": {"name": "Can change round stat", "content_type": 9, "codename": "change_roundstat"}}, {"model": "auth.permission", "pk": 35, "fields": {"name": "Can delete round stat", "content_type": 9, "codename": "delete_roundstat"}}, {"model": "auth.permission", "pk": 36, "fields": {"name": "Can view round stat", "content_type": 9, "codename": "view_roundstat"}}, {"model": "auth.permission", "pk": 37, "fields": {"name": "Can add user", "content_type": 10, "codename": "add_customuser"}}, {"model": "auth.permission", "pk": 38, "fields": {"name": "Can change user", "content_type": 10, "codename": "change_customuser"}}, {"model": "auth.permission", "pk": 39, "fields": {"name": "Can delete user", "content_type": 10, "codename": "delete_customuser"}}, {"model": "auth.permission", "pk": 40, "fields": {"name": "Can view user", "content_type": 10, "codename": "view_customuser"}}, {"model": "contenttypes.contenttype", "pk": 1, "fields": {"app_label": "admin", "model": "logentry"}}, {"model": "contenttypes.contenttype", "pk": 2, "fields": {"app_label": "auth", "model": "permission"}}, {"model": "contenttypes.contenttype", "pk": 3, "fields": {"app_label": "auth", "model": "group"}}, {"model": "contenttypes.contenttype", "pk": 4, "fields": {"app_label": "contenttypes", "model": "contenttype"}}, {"model": "contenttypes.contenttype", "pk": 5, "fields": {"app_label": "sessions", "model": "session"}}, {"model": "contenttypes.contenttype", "pk": 6, "fields": {"app_label": "market", "model": "market"}}, {"model": "contenttypes.contenttype", "pk": 7, "fields": {"app_label": "market", "model": "trader"}}, {"model": "contenttypes.contenttype", "pk": 8, "fields": {"app_label": "market", "model": "trade"}}, {"model": "contenttypes.contenttype", "pk": 9, "fields": {"app_label": "market", "model": "roundstat"}}, {"model": "contenttypes.contenttype", "pk": 10, "fields": {"app_label": "accounts", "model": "customuser"}}, {"model": "sessions.session", "pk": "owl7yo2g2wklud4pqk3tokd24476yonz", "fields": {"session_data": "eyJ0cmFkZXJfaWQiOjEsInVzZXJuYW1lIjoic1x1MDBmOHJlbiIsIm1hcmtldF9pZCI6IllGQ0daWkpBIn0:1mN9FN:cBT3XFyBIaESTcVhsB75LFBbt8SmvHp1P9rMR5OAj10", "expire_date": "2021-09-20T07:40:53.295Z"}}, {"model": "sessions.session", "pk": "qcl7t3e7uyjf54evj919jqlvy2iibfof", "fields": {"session_data": ".eJxVjDsOwjAQRO_iGll21p-Ykj5nsHb9wQHkSHFSIe5OLKWAYpp5b-bNPO5b8XtLq58juzLJLr8dYXim2kF8YL0vPCx1W2fiXeEnbXxaYnrdTvfvoGArx3o0AixFFNkgSBJKOaX1mG2Py0TBSJVMigDCDTKTBjiADQa1GSKyzxfO_DeA:1mN9EE:QFuo9hk5ukGZq_L-NFT4QufF9gEH8GtHQ3mv1vhLFvo", "expire_date": "2021-09-20T07:39:42.436Z"}}, {"model": "market.market", "pk": "GECQMFQS", "fields": {"product_name_singular": "baguette", "product_name_plural": "baguettes", "alpha": "105.0000", "beta": "17.5000", "theta": "14.5800", "initial_balance": "5000.00", "min_cost": "5.00", "max_cost": "15.00", "round": 0, "max_rounds": 15, "endless": false, "created_at": "2021-09-06T07:39:48.974Z", "created_by": 1}}, {"model": "market.market", "pk": "GSPOUXFM", "fields": {"product_name_singular": "baguette", "product_name_plural": "baguettes", "alpha": "105.0000", "beta": "17.5000", "theta": "14.5800", "initial_balance": "5000.00", "min_cost": "8.00", "max_cost": "8.00", "round": 0, "max_rounds": 15, "endless": false, "created_at": "2021-09-06T07:39:43.993Z", "created_by": 1}}, {"model": "market.market", "pk": "YFCGZZJA", "fields": {"product_name_singular": "lemonade", "product_name_plural": "lemonade", "alpha": "105.0000", "beta": "17.5000", "theta": "14.5800", "initial_balance": "1000.00", "min_cost": "8.00", "max_cost": "8.00", "round": 4, "max_rounds": 15, "endless": true, "created_at": "2021-09-06T07:40:40.496Z", "created_by": 1}}, {"model": "market.trader", "pk": 1, "fields": {"market": "YFCGZZJA", "name": "søren", "prod_cost": "8.00", "balance": "2608.50", "round_joined": 0, "created_at": "2021-09-06T07:40:53.288Z"}}, {"model": "market.trade", "pk": 1, "fields": {"trader": 1, "unit_price": "20.00", "unit_amount": 63, "round": 0, "was_forced": false, "demand": 47, "units_sold": 47, "profit": "436.00", "balance_after": "1436.00", "balance_before": "1000.00", "created_at": "2021-09-06T07:41:06.893Z"}}, {"model": "market.trade", "pk": 2, "fields": {"trader": 1, "unit_price": "18.40", "unit_amount": 63, "round": 1, "was_forced": false, "demand": 51, "units_sold": 51, "profit": "434.40", "balance_after": "1870.40", "balance_before": "1436.00", "created_at": "2021-09-06T07:41:40.143Z"}}, {"model": "market.trade", "pk": 3, "fields": {"trader": 1, "unit_price": "17.20", "unit_amount": 63, "round": 2, "was_forced": false, "demand": 55, "units_sold": 55, "profit": "442.00", "balance_after": "2312.40", "balance_before": "1870.40", "created_at": "2021-09-06T07:41:44.924Z"}}, {"model": "market.trade", "pk": 4, "fields": {"trader": 1, "unit_price": "12.70", "unit_amount": 63, "round": 3, "was_forced": false, "demand": 68, "units_sold": 63, "profit": "296.10", "balance_after": "2608.50", "balance_before": "2312.40", "created_at": "2021-09-06T07:41:49.541Z"}}, {"model": "market.roundstat", "pk": 1, "fields": {"market": "YFCGZZJA", "round": 0, "avg_price": "20.00", "avg_balance_after": "1436.00", "avg_amount": "63.00", "created_at": "2021-09-06T07:41:34.984Z"}}, {"model": "market.roundstat", "pk": 2, "fields": {"market": "YFCGZZJA", "round": 1, "avg_price": "18.40", "avg_balance_after": "1870.40", "avg_amount": "63.00", "created_at": "2021-09-06T07:41:40.275Z"}}, {"model": "market.roundstat", "pk": 3, "fields": {"market": "YFCGZZJA", "round": 2, "avg_price": "17.20", "avg_balance_after": "2312.40", "avg_amount": "63.00", "created_at": "2021-09-06T07:41:45.567Z"}}, {"model": "market.roundstat", "pk": 4, "fields": {"market": "YFCGZZJA", "round": 3, "avg_price": "12.70", "avg_balance_after": "2608.50", "avg_amount": "63.00", "created_at": "2021-09-06T07:41:49.848Z"}}, {"model": "accounts.customuser", "pk": 1, "fields": {"password": "pbkdf2_sha256$260000$303ZYgfsB1eWx7idyRDGlb$P2GfBvvF8uZFqtCbEjgQ9kk3JwZmdZAE6b6q/hpf9l4=", "last_login": "2021-09-06T07:39:42.432Z", "is_superuser": false, "username": "test", "first_name": "", "last_name": "", "email": "test@example.com", "is_staff": false, "is_active": true, "date_joined": "2021-09-06T07:39:33.041Z", "groups": [], "user_permissions": []}}]